autotests_coverage/__init__.py
autotests_coverage/config.py
autotests_coverage/reporter.py
autotests_coverage/request_schema_handler.py
autotests_coverage/uri.py
autotests_coverage/docs_writers/__init__.py
autotests_coverage/docs_writers/api_doc_writer.py
autotests_coverage/results_writers/__init__.py
autotests_coverage/results_writers/base_schemas_manager.py
autotests_coverage/results_writers/openapi_schemas_manager.py
autotests_coverage/results_writers/swagger_schemas_manager.py
autotests_coverage/swagger-coverage-commandline/bin/swagger-coverage-commandline
autotests_coverage/swagger-coverage-commandline/bin/swagger-coverage-commandline.bat
autotests_coverage/swagger-coverage-commandline/lib/btf-1.3.jar
autotests_coverage/swagger-coverage-commandline/lib/checker-compat-qual-2.5.5.jar
autotests_coverage/swagger-coverage-commandline/lib/checker-qual-3.12.0.jar
autotests_coverage/swagger-coverage-commandline/lib/commons-codec-1.11.jar
autotests_coverage/swagger-coverage-commandline/lib/commons-codec-1.9.jar
autotests_coverage/swagger-coverage-commandline/lib/commons-io-2.11.0.jar
autotests_coverage/swagger-coverage-commandline/lib/commons-io-2.6.jar
autotests_coverage/swagger-coverage-commandline/lib/commons-lang3-3.12.0.jar
autotests_coverage/swagger-coverage-commandline/lib/commons-lang3-3.7.jar
autotests_coverage/swagger-coverage-commandline/lib/commons-logging-1.2.jar
autotests_coverage/swagger-coverage-commandline/lib/error_prone_annotations-2.3.4.jar
autotests_coverage/swagger-coverage-commandline/lib/error_prone_annotations-2.7.1.jar
autotests_coverage/swagger-coverage-commandline/lib/failureaccess-1.0.1.jar
autotests_coverage/swagger-coverage-commandline/lib/freemarker-2.3.31.jar
autotests_coverage/swagger-coverage-commandline/lib/guava-28.2-android.jar
autotests_coverage/swagger-coverage-commandline/lib/guava-31.0.1-android.jar
autotests_coverage/swagger-coverage-commandline/lib/httpclient-4.5.13.jar
autotests_coverage-1.1.0.dist-info/licenses/LICENSE
autotests_coverage-1.1.0.dist-info/METADATA
autotests_coverage-1.1.0.dist-info/WHEEL
autotests_coverage-1.1.0.dist-info/top_level.txt
autotests_coverage-1.1.0.dist-info/RECORD
