Metadata-Version: 2.4
Name: autotests-coverage
Version: 1.1.0
Summary: Python adapter for "swagger-coverage" tool
Home-page: https://github.com/JamalZeynalov/swagger-coverage-py
Author: Jamal Zeinalov
Author-email: jamal.zeynalov@gmail.com
Classifier: Programming Language :: Python :: 3
Classifier: License :: OSI Approved :: MIT License
Classifier: Operating System :: OS Independent
Requires-Python: >=3.7
License-File: LICENSE
Requires-Dist: requests>=2.32.3
Requires-Dist: setuptools>=70.0.0
Requires-Dist: PyYAML>=6.0.2
Requires-Dist: pydantic>=2.11.1
Requires-Dist: filelock>=3.18.0
Dynamic: author
Dynamic: author-email
Dynamic: classifier
Dynamic: description
Dynamic: description-content-type
Dynamic: home-page
Dynamic: license-file
Dynamic: requires-dist
Dynamic: requires-python
Dynamic: summary
